base_client.py
utils.py
version.py
orquesta_dev-1.0.0.dist-info/LICENSE
orquesta_dev-1.0.0.dist-info/METADATA
orquesta_dev-1.0.0.dist-info/WHEEL
orquesta_dev-1.0.0.dist-info/top_level.txt
orquesta_dev-1.0.0.dist-info/RECORD
